smartmonkey/__init__.py
smartmonkey/client.py
smartmonkey/exceptions.py
smartmonkey/models.py
smartmonkey/optimize.py
smartmonkey/serializer.py
smartmonkey-1.0.2.dist-info/LICENSE
smartmonkey-1.0.2.dist-info/METADATA
smartmonkey-1.0.2.dist-info/WHEEL
smartmonkey-1.0.2.dist-info/top_level.txt
smartmonkey-1.0.2.dist-info/RECORD
