Metadata-Version: 2.1
Name: smartmonkey
Version: 1.0.2
Summary: Python client for Smartmonkey API Web Services
Home-page: https://github.com/smartmonkeyio/smartmonkey-services-python
License: Apache 2.0
Platform: Posix; MacOS X; Windows
Classifier: Development Status :: 4 - Beta
Classifier: Intended Audience :: Developers
Classifier: Operating System :: OS Independent
Classifier: Programming Language :: Python :: 2.7
Classifier: Programming Language :: Python :: 3.2
Classifier: Programming Language :: Python :: 3.4
Classifier: Programming Language :: Python :: 3.5
Classifier: Programming Language :: Python :: 3.6
Requires-Dist: requests (<3.0,>=2.11.1)
